valdar/__init__.py
valdar/core.py
valdar/status.py
valdar-1.1.0.dist-info/METADATA
valdar-1.1.0.dist-info/WHEEL
valdar-1.1.0.dist-info/top_level.txt
valdar-1.1.0.dist-info/RECORD
