Metadata-Version: 2.4
Name: valdar
Version: 1.1.0
Summary: Radar data validation and analysis tool
Author-email: Emmanuel Zerah <emmanuel.zerah@mobileye.com>
Requires-Python: >=3.7
Requires-Dist: numpy>=1.20
Requires-Dist: pandas>=1.3
Requires-Dist: devkit
